bbrl_utils/__init__.py
bbrl_utils/_version.py
bbrl_utils/algorithms.py
bbrl_utils/config.py
bbrl_utils/env.py
bbrl_utils/logger.py
bbrl_utils/nn.py
bbrl_utils/notebook.py
bbrl_utils/rl.code-workspace
bbrl_utils-1.1.1.dist-info/licenses/LICENSE
bbrl_utils-1.1.1.dist-info/METADATA
bbrl_utils-1.1.1.dist-info/WHEEL
bbrl_utils-1.1.1.dist-info/top_level.txt
bbrl_utils-1.1.1.dist-info/RECORD
