Metadata-Version: 2.4
Name: bbrl_utils
Version: 1.1.1
Summary: Utilities for notebooks built around BBRL
Author-email: Benjamin Piwowarski <benjamin@piwowarski.fr>
License: MIT
Project-URL: Repository, https://github.com/bpiwowar/bbrl_utils
License-File: LICENSE
Requires-Dist: easypip
Requires-Dist: bbrl>=1.0.1
Requires-Dist: moviepy>=1
Requires-Dist: bbrl_gymnasium>=1.0.0
Requires-Dist: tensorboard
Requires-Dist: pygame
Dynamic: license-file
